MANIFEST.in
setup.py
db/__init__.py
db/models.py
db/transfer_experiment.db
sjc_transfer_db.egg-info/PKG-INFO
sjc_transfer_db.egg-info/SOURCES.txt
sjc_transfer_db.egg-info/dependency_links.txt
sjc_transfer_db.egg-info/not-zip-safe
sjc_transfer_db.egg-info/requires.txt
sjc_transfer_db.egg-info/top_level.txt