Metadata-Version: 1.1
Name: sjc-transfer-db
Version: 0.11
Summary: San Jacinto College Transfer Database
Home-page: http://github.com/mattl3w1s/sjc_transfer_db
Author: Matt Lewis
Author-email: matthew.lewis@sjcd.edu
License: UNKNOWN
Platform: UNKNOWN
Classifier: Programming Language :: Python :: 3.6
